cuckoo_filter/__init__.py
cuckoo_filter/_version.py
cuckoo_filter/cuckoo.py
cuckoo_filter-1.0.6.dist-info/LICENSE
cuckoo_filter-1.0.6.dist-info/METADATA
cuckoo_filter-1.0.6.dist-info/WHEEL
cuckoo_filter-1.0.6.dist-info/top_level.txt
cuckoo_filter-1.0.6.dist-info/RECORD
