Metadata-Version: 2.1
Name: cuckoo_filter
Version: 1.0.6
Summary: Cuckoo Filter: Practically Better Than Bloom
Home-page: https://github.com/amoallim15/Cuckoo-Filter
Author: Ali Moallim
Author-email: amoallim15@gmail.com
License: GPLv3 License
Platform: UNKNOWN
Classifier: Development Status :: 2 - Pre-Alpha
Classifier: Intended Audience :: Developers
Classifier: Programming Language :: Python :: 3 :: Only
Classifier: Programming Language :: Python :: 3.6
Classifier: Programming Language :: Python :: 3.7
Classifier: Programming Language :: Python :: 3.8
Classifier: Topic :: Software Development :: Libraries
Requires-Python: >=3.6
Provides-Extra: dev
